{
    "schema": {
        "type": "object",
        "properties": {
            "empid": {
                "type": "string"
            },
            "empname": {
                "type": "object",
                "properties": {
                    "title": {
                        "type": "string"
                    },
                    "firstnames": {
                        "type": "array",
                        "items": {
                            "type": "object",
                            "properties": {
                                "firstname": {
                                    "type": "string"
                                },
                                "abbreviation": {
                                    "type": "string"
                                }
                            },
                            "required": ["firstname", "abbreviation"]
                        },
                        "minItems": 1
                    },
                    "lastname": {
                        "type": "string"
                    },
                    "required": ["firstnames", "lastname"]
                }
            },
            "projects": {
                "type": "array",
                "items": {
                    "type": "object",
                    "properties": {
                        "work_in_project": {
                            "type": "string"
                        },
                        "pid": {
                            "type": "string"
                        }
                    },
                    "required": ["work_in_project", "pid"]
                }
            },
            "skill": {
                "type": "array",
                "items": {
                    "type": "string"
                }
            }
        },
        "required": ["empid", "empname", "projects", "skill"]
    },
    "data": [
        {
            "empid": "6394",
            "firstnames": [{
                "firstname": "Sam",
                "abbreviation": "S."
            }],
            "lastname": "Jones",
            "projects": [],
            "skill": ["cooking", "dancing"]
        },
        {
            "empid": "0815",
            "firstnames": [{
                "firstname": "Patricia",
                "abbreviation": "P."
            }],
            "lastname": "May",
            "projects": [],
            "skill": ["programming"]
        }

    ]
}